fourier_approximation/__init__.py
fourier_approximation/approximation.py
tests/__init__.py
tests/test_approximation.py
fourier_approximation-0.1.0.dist-info/METADATA
fourier_approximation-0.1.0.dist-info/WHEEL
fourier_approximation-0.1.0.dist-info/top_level.txt
fourier_approximation-0.1.0.dist-info/RECORD
