Metadata-Version: 2.1
Name: fourier_approximation
Version: 0.1.0
Summary: A package to approximate Fourier transforms
Home-page: https://github.com/Lilian-Mo/fourier_approximation
Author: Lilian-Mo
Author-email: ignifin@gmail.com
Classifier: Programming Language :: Python :: 3
Classifier: License :: OSI Approved :: MIT License
Classifier: Operating System :: OS Independent
Requires-Python: >=3.6
Requires-Dist: numpy
